sqlakeyset/__init__.py
sqlakeyset/asyncio.py
sqlakeyset/columns.py
sqlakeyset/constants.py
sqlakeyset/paging.py
sqlakeyset/py.typed
sqlakeyset/results.py
sqlakeyset/sqla.py
sqlakeyset/sqla13.py
sqlakeyset/sqla14.py
sqlakeyset/sqla20.py
sqlakeyset/types.py
sqlakeyset/serial/__init__.py
sqlakeyset/serial/serial.py
sqlakeyset-2.0.1762823545.dist-info/METADATA
sqlakeyset-2.0.1762823545.dist-info/WHEEL
sqlakeyset-2.0.1762823545.dist-info/licenses/LICENSE
sqlakeyset-2.0.1762823545.dist-info/RECORD
