Metadata-Version: 2.4
Name: sqlakeyset
Version: 2.0.1762823545
Summary: offset-free paging for sqlalchemy
Project-URL: homepage, https://github.com/djrobstep/sqlakeyset
Project-URL: repository, https://github.com/djrobstep/sqlakeyset
Author-email: Robert Lechte <robertlechte@gmail.com>, Anthony Carapetis <anthony.carapetis@gmail.com>
License: Unlicense
License-File: LICENSE
Requires-Python: >=3.9
Requires-Dist: packaging>=20.0
Requires-Dist: python-dateutil>=2.0
Requires-Dist: sqlalchemy>=1.3.11
Requires-Dist: typing-extensions<5,>=4.7; python_version < '3.13'
